Ligare/web/__init__.py
Ligare/web/application.py
Ligare/web/config.py
Ligare/web/py.typed
Ligare/web/response.py
Ligare/web/encryption/__init__.py
Ligare/web/host/__init__.py
Ligare/web/middleware/__init__.py
Ligare/web/middleware/consts.py
Ligare/web/middleware/context.py
Ligare/web/middleware/dependency_injection.py
Ligare/web/middleware/sso.py
Ligare/web/middleware/feature_flags/__init__.py
Ligare/web/middleware/flask/__init__.py
Ligare/web/middleware/openapi/__init__.py
Ligare/web/middleware/openapi/cors.py
Ligare/web/scaffolding/__init__.py
Ligare/web/scaffolding/__main__.py
Ligare/web/scaffolding/scaffolder.py
Ligare/web/scaffolding/templates/base/LICENSE.md.j2
Ligare/web/scaffolding/templates/base/Makefile.j2
Ligare/web/scaffolding/templates/base/README.md.j2
Ligare/web/scaffolding/templates/base/pyproject.toml.j2
Ligare/web/scaffolding/templates/base/docs/CONFIGURATION.md.j2
Ligare/web/scaffolding/templates/base/{{application.module_name}}/__init__.py.j2
Ligare/web/scaffolding/templates/base/{{application.module_name}}/__main__.py.j2
Ligare/web/scaffolding/templates/base/{{application.module_name}}/_app_type.py.j2
Ligare/web/scaffolding/templates/base/{{application.module_name}}/_version.py.j2
Ligare/web/scaffolding/templates/base/{{application.module_name}}/endpoints/__init__.py.j2
Ligare/web/scaffolding/templates/base/{{application.module_name}}/endpoints/application.py.j2
Ligare/web/scaffolding/templates/basic/{{application.module_name}}/config.toml.j2
Ligare/web/scaffolding/templates/openapi/{{application.module_name}}/__main__.py.j2
Ligare/web/scaffolding/templates/openapi/{{application.module_name}}/_app_type.py.j2
Ligare/web/scaffolding/templates/openapi/{{application.module_name}}/config.toml.j2
Ligare/web/scaffolding/templates/openapi/{{application.module_name}}/openapi.yaml.j2
Ligare/web/scaffolding/templates/openapi/{{application.module_name}}/endpoints/application.py.j2
ligare_web-0.7.2.dist-info/licenses/LICENSE.md
ligare_web-0.7.2.dist-info/METADATA
ligare_web-0.7.2.dist-info/WHEEL
ligare_web-0.7.2.dist-info/entry_points.txt
ligare_web-0.7.2.dist-info/top_level.txt
ligare_web-0.7.2.dist-info/RECORD
